cython_methods.cpython-37m-darwin.so
fib.cpython-37m-darwin.so
rankfm/__init__.py
rankfm/_rankfm.cpython-37m-darwin.so
rankfm/cython_methods.cpython-37m-darwin.so
rankfm/evaluation.py
rankfm/rankfm.py
rankfm/utils.py
rankfm-0.2.5.dist-info/LICENSE
rankfm-0.2.5.dist-info/METADATA
rankfm-0.2.5.dist-info/WHEEL
rankfm-0.2.5.dist-info/top_level.txt
rankfm-0.2.5.dist-info/RECORD
