Metadata-Version: 2.1
Name: rankfm
Version: 0.2.5
Summary: a python implementation of the generic factorization machines model class adapted for collaborative filtering recommendation problems with implicit feedback user-item interaction data and (optionally) additional user/item side features
Home-page: https://github.com/etlundquist/rankfm
Author: Eric Lundquist
Author-email: e.t.lundquist@gmail.com
License: GNU General Public License v3.0
Keywords: machine,learning,recommendation,factorization,machines,implicit
Platform: UNKNOWN
Requires-Python: >=3.6
Requires-Dist: numpy (>=1.15)
Requires-Dist: pandas (>=0.24)
